onestep/__init__.py
onestep/_utils.py
onestep/cli.py
onestep/cron.py
onestep/exception.py
onestep/message.py
onestep/onestep.py
onestep/retry.py
onestep/signal.py
onestep/state.py
onestep/worker.py
onestep/broker/__init__.py
onestep/broker/base.py
onestep/broker/cron.py
onestep/broker/memory.py
onestep/broker/mysql.py
onestep/broker/rabbitmq.py
onestep/broker/webhook.py
onestep/broker/redis/__init__.py
onestep/broker/redis/pubsub.py
onestep/broker/redis/stream.py
onestep/broker/sqs/__init__.py
onestep/broker/sqs/sns.py
onestep/broker/sqs/sqs.py
onestep/middleware/__init__.py
onestep/middleware/base.py
onestep/middleware/config.py
onestep/middleware/unique.py
onestep-0.5.1.dist-info/METADATA
onestep-0.5.1.dist-info/WHEEL
onestep-0.5.1.dist-info/entry_points.txt
onestep-0.5.1.dist-info/RECORD
