Metadata-Version: 2.4
Name: onestep
Version: 0.5.1
Summary: 仅需一步，轻松实现分布式异步任务。
Author-email: miclon <jcnd@163.com>
License: MIT
Keywords: async,distributed,queue,task
Classifier: Development Status :: 4 - Beta
Classifier: Intended Audience :: Developers
Classifier: License :: OSI Approved :: MIT License
Classifier: Programming Language :: Python :: 3
Classifier: Programming Language :: Python :: 3.8
Classifier: Programming Language :: Python :: 3.9
Classifier: Programming Language :: Python :: 3.10
Classifier: Programming Language :: Python :: 3.11
Classifier: Programming Language :: Python :: 3.12
Requires-Python: >=3.8
Requires-Dist: asgiref>=3.6.0
Requires-Dist: blinker>=1.5
Requires-Dist: croniter>=1.3.8
Requires-Dist: use-rabbitmq>=0.2.1
Provides-Extra: dev
Requires-Dist: autopep8>=2.0.2; extra == 'dev'
Requires-Dist: loguru>=0.6.0; extra == 'dev'
Requires-Dist: nacos-sdk-python>=0.1.12; extra == 'dev'
Requires-Dist: redis>=4.5.1; extra == 'dev'
Requires-Dist: use-redis>=0.1.92; extra == 'dev'
Provides-Extra: mysql
Requires-Dist: use-mysql>=0.0.4; extra == 'mysql'
Provides-Extra: redis
Requires-Dist: use-redis>=0.1.6; extra == 'redis'
Provides-Extra: sqs
Requires-Dist: use-sqs>=0.1.0; extra == 'sqs'
Provides-Extra: test
Requires-Dist: httpx>=0.23.3; extra == 'test'
Requires-Dist: pytest>=7.2.2; extra == 'test'
Requires-Dist: redis>=4.5.1; extra == 'test'
